dfes/__init__.py
dfes/_version.py
dfes/dfes.py
dfes-1.0.4.dist-info/METADATA
dfes-1.0.4.dist-info/WHEEL
dfes-1.0.4.dist-info/entry_points.txt
dfes-1.0.4.dist-info/top_level.txt
dfes-1.0.4.dist-info/RECORD
